__init__.py
py4heappe_cli.py
py4heappe/__init__.py
py4heappe/heappe_v4/__init__.py
py4heappe/heappe_v4/cli/__init__.py
py4heappe/heappe_v4/cli/auth.py
py4heappe/heappe_v4/cli/command_template.py
py4heappe/heappe_v4/cli/configuration.py
py4heappe/heappe_v4/cli/information.py
py4heappe/heappe_v4/cli/job_management.py
py4heappe/heappe_v4/cli/report.py
py4heappe/heappe_v4/core/__init__.py
py4heappe/heappe_v4/core/api_client.py
py4heappe/heappe_v4/core/configuration.py
py4heappe/heappe_v4/core/rest.py
py4heappe/heappe_v4/core/api/__init__.py
py4heappe/heappe_v4/core/api/cluster_information_api.py
py4heappe/heappe_v4/core/api/data_transfer_api.py
py4heappe/heappe_v4/core/api/file_transfer_api.py
py4heappe/heappe_v4/core/api/job_management_api.py
py4heappe/heappe_v4/core/api/job_reporting_api.py
py4heappe/heappe_v4/core/api/management_api.py
py4heappe/heappe_v4/core/api/user_and_limitation_management_api.py
py4heappe/heappe_v4/core/base/__init__.py
py4heappe/heappe_v4/core/base/exceptions.py
py4heappe/heappe_v4/core/base/logger.py
py4heappe/heappe_v4/core/base/utils.py
py4heappe/heappe_v4/core/models/__init__.py
py4heappe/heappe_v4/core/models/adaptor_user.py
py4heappe/heappe_v4/core/models/adaptor_user_group.py
py4heappe/heappe_v4/core/models/adaptor_user_role.py
py4heappe/heappe_v4/core/models/adaptor_user_role_ext.py
py4heappe/heappe_v4/core/models/adaptor_user_role_type.py
py4heappe/heappe_v4/core/models/adaptor_user_type.py
py4heappe/heappe_v4/core/models/adaptor_user_user_group_role.py
py4heappe/heappe_v4/core/models/allocated_nodes_ips_model.py
py4heappe/heappe_v4/core/models/authenticate_lexis_token_model.py
py4heappe/heappe_v4/core/models/authenticate_user_digital_signature_model.py
py4heappe/heappe_v4/core/models/authenticate_user_open_id_model.py
py4heappe/heappe_v4/core/models/authenticate_user_open_id_open_stack_model.py
py4heappe/heappe_v4/core/models/authenticate_user_password_model.py
py4heappe/heappe_v4/core/models/authentication_credentials.py
py4heappe-2.3.0.dist-info/licenses/LICENSE
py4heappe-2.3.0.dist-info/METADATA
py4heappe-2.3.0.dist-info/WHEEL
py4heappe-2.3.0.dist-info/entry_points.txt
py4heappe-2.3.0.dist-info/top_level.txt
py4heappe-2.3.0.dist-info/RECORD
