Metadata-Version: 2.4
Name: Py4HEAppE
Version: 2.3.0
Summary: Py4HEAppE is client library for easy access to HEAppE Middleware
Author-email: IT4Innovations <support.heappe@it4i.cz>
License-Expression: MIT
Project-URL: Homepage, https://github.com/It4innovations/Py4HEAppE
Project-URL: Repository, https://github.com/It4innovations/Py4HEAppE.git
Project-URL: Issues, https://github.com/It4innovations/Py4HEAppE/issues
Keywords: LEXIS,HEAppE,Client Library
Classifier: Programming Language :: Python :: 3
Classifier: Operating System :: OS Independent
Requires-Python: >=3.11
License-File: LICENSE
Requires-Dist: paramiko==4.0.0
Requires-Dist: scp==0.15.0
Requires-Dist: urllib3==2.5.0
Requires-Dist: certifi==2025.8.3
Requires-Dist: six==1.17.0
Requires-Dist: click==8.3.0
Requires-Dist: typer>=0.15.0
Requires-Dist: python-dotenv>=0.21.1
Requires-Dist: validators==0.35.0
Dynamic: license-file
